README.md
cppumockify.py
setup.py
CppUMockify.egg-info/PKG-INFO
CppUMockify.egg-info/SOURCES.txt
CppUMockify.egg-info/dependency_links.txt
CppUMockify.egg-info/entry_points.txt
CppUMockify.egg-info/requires.txt
CppUMockify.egg-info/top_level.txt