Metadata-Version: 2.1
Name: CppUMockify
Version: 0.0.6
Summary: Generate CppUMock implementations
Home-page: https://github.com/spoorcc/cppumockify
Author: spoorcc
License: UNKNOWN
Project-URL: Bug Reports, https://github.com/spoorcc/cppumockify/issues
Project-URL: Source, https://github.com/spoorcc/cppumockify/
Keywords: cpputest cppumock pycparser
Platform: UNKNOWN
Classifier: Development Status :: 3 - Alpha
Classifier: Intended Audience :: Developers
Classifier: Topic :: Software Development :: Build Tools
Classifier: License :: OSI Approved :: ISC License (ISCL)
Classifier: Programming Language :: Python :: 3
Classifier: Programming Language :: Python :: 3.4
Classifier: Programming Language :: Python :: 3.5
Classifier: Programming Language :: Python :: 3.6
